hallucination_detector/__init__.py
hallucination_detector/analyzers.py
hallucination_detector/detector.py
hallucination_detector/reporters.py
hallucination_detector/types.py
hallucination_detector/validators.py
hallucination_detector-1.0.0.dist-info/licenses/LICENSE
hallucination_detector-1.0.0.dist-info/METADATA
hallucination_detector-1.0.0.dist-info/WHEEL
hallucination_detector-1.0.0.dist-info/entry_points.txt
hallucination_detector-1.0.0.dist-info/top_level.txt
hallucination_detector-1.0.0.dist-info/RECORD
