Metadata-Version: 2.4
Name: hallucination-detector
Version: 1.0.0
Summary: Production-ready hallucination detection for LLM outputs
Author-email: Pranay M <pranay@example.com>
Maintainer-email: Pranay M <pranay@example.com>
License: MIT
Project-URL: Homepage, https://github.com/pranaym/hallucination-detector
Project-URL: Documentation, https://hallucination-detector.readthedocs.io
Project-URL: Repository, https://github.com/pranaym/hallucination-detector
Project-URL: Issues, https://github.com/pranaym/hallucination-detector/issues
Project-URL: Changelog, https://github.com/pranaym/hallucination-detector/blob/main/CHANGELOG.md
Keywords: llm,hallucination,detection,ai,machine-learning,nlp,fact-checking,verification,chatgpt,gpt,claude,openai,anthropic
Classifier: Development Status :: 5 - Production/Stable
Classifier: Intended Audience :: Developers
Classifier: Intended Audience :: Science/Research
Classifier: License :: OSI Approved :: MIT License
Classifier: Operating System :: OS Independent
Classifier: Programming Language :: Python :: 3
Classifier: Programming Language :: Python :: 3.8
Classifier: Programming Language :: Python :: 3.9
Classifier: Programming Language :: Python :: 3.10
Classifier: Programming Language :: Python :: 3.11
Classifier: Programming Language :: Python :: 3.12
Classifier: Topic :: Scientific/Engineering :: Artificial Intelligence
Classifier: Topic :: Text Processing :: Linguistic
Classifier: Typing :: Typed
Requires-Python: >=3.8
License-File: LICENSE
Provides-Extra: full
Requires-Dist: sentence-transformers>=2.2.0; extra == "full"
Requires-Dist: spacy>=3.0.0; extra == "full"
Requires-Dist: numpy>=1.20.0; extra == "full"
Provides-Extra: dev
Requires-Dist: pytest>=7.0.0; extra == "dev"
Requires-Dist: pytest-cov>=4.0.0; extra == "dev"
Requires-Dist: pytest-asyncio>=0.21.0; extra == "dev"
Requires-Dist: black>=23.0.0; extra == "dev"
Requires-Dist: isort>=5.12.0; extra == "dev"
Requires-Dist: mypy>=1.0.0; extra == "dev"
Requires-Dist: ruff>=0.1.0; extra == "dev"
Provides-Extra: docs
Requires-Dist: sphinx>=6.0.0; extra == "docs"
Requires-Dist: sphinx-rtd-theme>=1.3.0; extra == "docs"
Requires-Dist: myst-parser>=2.0.0; extra == "docs"
Dynamic: license-file
